fffbnf.py
fffbnf_include.py
fffbnf_lex.py
fffbnf_parser.py
ffflex.py
ffflex_include.py
ffflex_lex.py
ffflex_parser.py
ffflex_template.py
fffmain.py
fffparser_template.py
fffpylinker.py
frontend_for_free-0.5.0.dist-info/LICENSE
frontend_for_free-0.5.0.dist-info/METADATA
frontend_for_free-0.5.0.dist-info/WHEEL
frontend_for_free-0.5.0.dist-info/entry_points.txt
frontend_for_free-0.5.0.dist-info/top_level.txt
frontend_for_free-0.5.0.dist-info/RECORD
