Metadata-Version: 2.1
Name: frontend-for-free
Version: 0.5.0
Summary: Statically generating standablone regex-based lexers and highly optimized LL(k) parsers
Home-page: https://github.com/thautwarm/frontend-for-free
Author: thautwarm
Author-email: twshere@outlook.com
License: MIT
Keywords: parser,lexer,context-free
Platform: any
Classifier: Programming Language :: Python :: 3.6
Classifier: Programming Language :: Python :: 3.7
Classifier: Programming Language :: Python :: 3.8
Classifier: Programming Language :: Python :: 3.9
Classifier: Programming Language :: Python :: Implementation :: CPython
License-File: LICENSE
Requires-Dist: ast-compat
Requires-Dist: wisepy2
Requires-Dist: attrs
